LICENSE
README.md
requirements.txt
setup.py
bin/protoweb
examples/blog/README.txt
examples/blog/data/first.json
examples/blog/data/index.json
examples/blog/data/second.json
examples/blog/data/third.json
examples/blog/static/css/base.css
examples/blog/static/js/simple.js
examples/blog/templates/base.html
examples/blog/templates/first.html
examples/blog/templates/index.html
examples/blog/templates/second.html
examples/blog/templates/third.html
protoweb/__init__.py
protoweb.egg-info/PKG-INFO
protoweb.egg-info/PKG_INFO.txt
protoweb.egg-info/SOURCES.txt
protoweb.egg-info/dependency_links.txt
protoweb.egg-info/requires.txt
protoweb.egg-info/top_level.txt
protoweb/fs/__init__.py
protoweb/fs/content.py
protoweb/processors/__init__.py
protoweb/processors/cyclone_template_processor.py
protoweb/processors/less_processor.py
protoweb/processors/processor.py
protoweb/server/__init__.py
protoweb/server/handler.py
protoweb/server/server.py
protoweb/util/__init__.py
protoweb/util/options.py
protoweb/util/runnable.py