Metadata-Version: 1.1
Name: protoweb
Version: 0.1.0-alpha
Summary: a very simple Cyclone web development mock tool
Home-page: https://github.com/vltr/protoweb
Author: Richard Kuesters
Author-email: rkuesters@gmail.com
License: http://opensource.org/licenses/MIT
Keywords: python cyclone web development mock
Platform: UNKNOWN
Classifier: Development Status :: 3 - Alpha
Classifier: Environment :: Console
Classifier: Intended Audience :: Developers
Classifier: License :: OSI Approved :: MIT License
Classifier: Operating System :: POSIX
Classifier: Programming Language :: Python
Classifier: Programming Language :: Python :: 2
Classifier: Topic :: Internet :: WWW/HTTP :: Dynamic Content
Classifier: Topic :: Software Development
Classifier: Topic :: Software Development :: User Interfaces
Classifier: Topic :: Text Processing :: Markup
Classifier: Topic :: Utilities
